single-cycle/data_memory/data_memory.v
module data_memory(
    input [31:0] in_address,
    input [31:0] in_write_data,
    input reset,
    input clk,
    input in_write_enable,
    output [31:0] out_data
);

    reg [63:0] memory [31:0];
    always @(posedge clk or negedge reset) begin
        if (!reset) begin
            for (integer i = 0; i < 64; i = i + 1) begin
                memory[i] = 32'b0;
            end
        end
        if (in_write_enable) begin
            memory[in_address] <= in_write_data;
        end
    end
    assign out_data = memory[in_address];
endmodule

single-cycle/data_memory/data_memory_tb.v
module data_memory_tb ();

reg [31:0] in_address;
reg [31:0] in_write_data;
reg clk;
reg reset;
reg in_write_enable;
wire [31:0] out_data;

data_memory DUT(
    .in_address(in_address),
    .in_write_data(in_write_data),
    .clk(clk),
    .in_write_enable(in_write_enable),
    .reset(reset),
    .out_data(out_data)
);

initial begin
    clk = 0;
    forever #5 clk = ~clk;
end

initial begin
    #100 $finish;
end

initial begin
    $dumpfile("data_memory.vcd");
    $dumpvars(0, data_memory_tb);
end

initial begin
    reset = 1;
    #10 
    reset = 0; in_write_enable = 0; in_address = 0; in_write_data = 0;
    #10
    in_write_enable = 1; in_write_data = 10; in_address = 0;
    #10
    in_write_enable = 1; in_write_data = 20; in_address = 1;
    #10;
    in_write_enable = 0; in_address = 0;
    #10;
    in_write_enable = 0; in_address = 1;
    #10;
end





endmodule

single-cycle/data_memory/data_memory.vcd
$date
	Sun May 18 10:50:55 2025
$end
$version
	Icarus Verilog
$end
$timescale
	1s
$end
$scope module data_memory_tb $end
$var wire 32 ! out_data [31:0] $end
$var reg 1 " clk $end
$var reg 32 # in_address [31:0] $end
$var reg 32 $ in_write_data [31:0] $end
$var reg 1 % in_write_enable $end
$var reg 1 & reset $end
$scope module DUT $end
$var wire 1 " clk $end
$var wire 32 ' in_address [31:0] $end
$var wire 32 ( in_write_data [31:0] $end
$var wire 1 % in_write_enable $end
$var wire 1 & reset $end
$var wire 32 ) out_data [31:0] $end
$scope begin $ivl_for_loop0 $end
$var integer 32 * i [31:0] $end
$upscope $end
$upscope $end
$upscope $end
$enddefinitions $end
$comment Show the parameter values. $end
$dumpall
$end
#0
$dumpvars
bx *
bx )
bx (
bx '
1&
x%
bx $
bx #
0"
bx !
$end
#5
1"
#10
b0 !
b0 )
b1000000 *
0"
b0 $
b0 (
b0 #
b0 '
0%
0&
#15
b1000000 *
1"
#20
0"
b1010 $
b1010 (
1%
#25
b1010 !
b1010 )
b1000000 *
1"
#30
b0 !
b0 )
0"
b1 #
b1 '
b10100 $
b10100 (
#35
b10100 !
b10100 )
b1000000 *
1"
#40
0"
#45
b10100 !
b10100 )
b1000000 *
1"
#50
0"
#55
b10100 !
b10100 )
b1000000 *
1"
#60
0"
#65
b10100 !
b10100 )
b1000000 *
1"
#70
0"
#75
b10100 !
b10100 )
b1000000 *
1"
#80
0"
#85
b10100 !
b10100 )
b1000000 *
1"
#90
0"
#95
b10100 !
b10100 )
b1000000 *
1"
