single-cycle/register_file/register_file.v
module register_file(
    input [4:0] in_read1_address,
    input [4:0] in_read2_address,
    input [4:0] in_write_address,
    input [31:0] in_write_data,
    input clk,
    input in_write_enable,
    input reset,
    output [31:0] out_read1_data,
    output [31:0] out_read2_data
);

reg [31:0] registers [31:0];

always @(posedge clk or negedge reset) begin
    if (reset) begin
        for (integer i = 0; i < 32; i = i + 1) begin
            registers[i] = 32'b0;
        end
    end 
    else begin
        if (in_write_enable) begin
            if (in_write_address != 0) begin // $x0 is always 0
                registers[in_write_address] <= in_write_data;
            end
        end
    end
end

assign out_read1_data = registers[in_read1_address];
assign out_read2_data = registers[in_read2_address];

endmodule

single-cycle/register_file_tb.v
// `include "register_file.v"

module register_file_tb ();

reg [4:0] in_read1_address;
reg [4:0] in_read2_address;
reg [4:0] in_write_address;
reg [31:0] in_write_data;
reg clk;
reg in_write_enable;
reg reset;
wire [31:0] out_read1_data;
wire [31:0] out_read2_data;

register_file DUT(
    .in_read1_address(in_read1_address),
    .in_read2_address(in_read2_address),
    .in_write_address(in_write_address),
    .in_write_data(in_write_data),
    .clk(clk),
    .in_write_enable(in_write_enable),
    .reset(reset),
    .out_read1_data(out_read1_data),
    .out_read2_data(out_read2_data)
);

initial begin
    clk = 0;
    forever #5 clk = ~clk;
end

initial begin
    #100 $finish;
end

initial begin
    $dumpfile("register_file.vcd");
    $dumpvars(0, register_file_tb);
end

initial begin
    reset = 1;
    #10 
    reset = 0; in_write_enable = 0; in_read1_address = 0; in_read2_address = 0; in_write_address = 0; in_write_data = 0;
    #10
    in_write_enable = 1; in_write_data = 10; in_write_address = 0; in_read1_address = 0; in_read2_address = 1;
    #10
    in_write_enable = 1; in_write_data = 20; in_write_address = 1; in_read1_address = 0; in_read2_address = 1;
    #10
    in_write_enable = 1; in_write_data = 30; in_write_address = 5; in_read1_address = 1; in_read2_address = 5;
    #10;
end





endmodule

single-cycle/register_file/register_file.vcd
$date
	Thu May 15 21:45:03 2025
$end
$version
	Icarus Verilog
$end
$timescale
	1s
$end
$scope module register_file_tb $end
$var wire 32 ! out_read2_data [31:0] $end
$var wire 32 " out_read1_data [31:0] $end
$var reg 1 # clk $end
$var reg 5 $ in_read1_address [4:0] $end
$var reg 5 % in_read2_address [4:0] $end
$var reg 5 & in_write_address [4:0] $end
$var reg 32 ' in_write_data [31:0] $end
$var reg 1 ( in_write_enable $end
$var reg 1 ) reset $end
$scope module DUT $end
$var wire 1 # clk $end
$var wire 5 * in_read1_address [4:0] $end
$var wire 5 + in_read2_address [4:0] $end
$var wire 5 , in_write_address [4:0] $end
$var wire 32 - in_write_data [31:0] $end
$var wire 1 ( in_write_enable $end
$var wire 32 . out_read1_data [31:0] $end
$var wire 32 / out_read2_data [31:0] $end
$var wire 1 ) reset $end
$scope begin $ivl_for_loop0 $end
$var integer 32 0 i [31:0] $end
$upscope $end
$upscope $end
$upscope $end
$enddefinitions $end
$comment Show the parameter values. $end
$dumpall
$end
#0
$dumpvars
b100000 0
bx /
bx .
bx -
bx ,
bx +
bx *
1)
x(
bx '
bx &
bx %
bx $
0#
bx "
bx !
$end
#5
b100000 0
1#
#10
0#
b0 '
b0 -
b0 &
b0 ,
b0 !
b0 /
b0 %
b0 +
b0 "
b0 .
b0 $
b0 *
0(
0)
#15
1#
#20
0#
b1 %
b1 +
b1010 '
b1010 -
1(
#25
1#
#30
0#
b1 &
b1 ,
b10100 '
b10100 -
#35
b10100 !
b10100 /
1#
#40
0#
b0 !
b0 /
b101 %
b101 +
b10100 "
b10100 .
b1 $
b1 *
b101 &
b101 ,
b11110 '
b11110 -
#45
b11110 !
b11110 /
1#
