single-cycle/ALU/ALU.v
module ALU (
    input [31:0] in_data1,
    input [31:0] in_data2,
    input [3:0] in_select,
    output reg [31:0] out_data
);

// {[2:0] funct3, funct7} as ALU Op Code
localparam ADD = 4'b0000;
localparam SUB = 4'b0000;
localparam XOR = 4'b1000;
localparam OR = 4'b1100;
localparam AND = 4'b1110;
localparam SHIFT_LEFT = 4'b0010;
localparam SHIFT_RIGHT_LOGICAL = 4'b1010;
localparam SHIFT_RIGHT_ARITHMETIC = 4'b1011;
localparam SET_LESS = 4'b0100;
localparam SET_LESS_UNSIGNED = 4'b0110;

always @* begin
    case (in_select)
        ADD: begin 
            out_data = in_data1 + in_data2;
        end
        SUB: begin
            out_data = in_data1 - in_data2;
        end
        XOR: begin
            out_data = in_data1 ^ in_data2;
        end
        OR: begin
            out_data = in_data1 | in_data2;
        end
        AND: begin
            out_data = in_data1 & in_data2;
        end
        SHIFT_LEFT: begin
            out_data = in_data1 << in_data2;
        end
        SHIFT_RIGHT_LOGICAL: begin
            out_data = in_data1 >> in_data2;
        end
        SHIFT_RIGHT_ARITHMETIC: begin
            out_data = $signed(in_data1) >>> in_data2;
        end
        SET_LESS: begin
            out_data = $signed(in_data1) < $signed(in_data2);
        end
        SET_LESS_UNSIGNED: begin
            out_data = in_data1 < in_data2;
        end
        default: begin
           out_data = 31'b0;
        end
    endcase
end

endmodule

single-cycle/ALU/ALU_tb.v
module ALU_tb ();

reg [31:0] in_data1;
reg [31:0] in_data2;
reg [3:0] in_select;
wire [31:0] out_data;

// {[2:0] funct3, funct7} as ALU Op Code
localparam ADD = 4'b0000;
localparam SUB = 4'b0001;
localparam XOR = 4'b1000;
localparam OR = 4'b1100;
localparam AND = 4'b1110;
localparam SHIFT_LEFT = 4'b0010;
localparam SHIFT_RIGHT_LOGICAL = 4'b1010;
localparam SHIFT_RIGHT_ARITHMETIC = 4'b1011;
localparam SET_LESS = 4'b0100;
localparam SET_LESS_UNSIGNED = 4'b0110;


ALU DUT(
    .in_data1(in_data1),
    .in_data2(in_data2),
    .in_select(in_select),
    .out_data(out_data)
);

initial begin
    #200 $finish;
end

initial begin
    $dumpfile("ALU.vcd");
    $dumpvars(0, ALU_tb);
end

initial begin
    in_data1 = 0; in_data2 = 0; in_select = ADD; #10; // 0
    in_data1 = 1; in_data2 = 2; in_select = ADD; #10; // 3
    in_data1 = 1; in_data2 = 2; in_select = SUB; #10; // -1
    in_data1 = 2; in_data2 = 4; in_select = XOR; #10; // 6
    in_data1 = 3; in_data2 = 4; in_select = OR; #10; // 7
    in_data1 = 3; in_data2 = 2; in_select = AND; #10; // 2
    in_data1 = 1; in_data2 = 5; in_select = SHIFT_LEFT; #10; // 32
    in_data1 = 17; in_data2 = 1; in_select = SHIFT_RIGHT_LOGICAL; #10; // 8
    in_data1 = -1; in_data2 = 2; in_select = SHIFT_RIGHT_ARITHMETIC; #10; // -1
    in_data1 = -10; in_data2 = 5; in_select = SET_LESS; #10; // 1
    in_data1 = 10; in_data2 = 5; in_select = SET_LESS; #10; // 0
    in_data1 = -10; in_data2 = 5; in_select = SET_LESS_UNSIGNED; #10; // 0
    in_data1 = 10; in_data2 = 5; in_select = SET_LESS_UNSIGNED; #10; // 0
    in_data1 = 9; in_data2 = 9; in_select = 8; #10; // 0
end

endmodule

single-cycle/ALU/ALU.vcd
$date
	Sat May 17 15:39:44 2025
$end
$version
	Icarus Verilog
$end
$timescale
	1s
$end
$scope module ALU_tb $end
$var wire 32 ! out_data [31:0] $end
$var parameter 4 " ADD $end
$var parameter 4 # AND $end
$var parameter 4 $ OR $end
$var parameter 4 % SET_LESS $end
$var parameter 4 & SET_LESS_UNSIGNED $end
$var parameter 4 ' SHIFT_LEFT $end
$var parameter 4 ( SHIFT_RIGHT_ARITHMETIC $end
$var parameter 4 ) SHIFT_RIGHT_LOGICAL $end
$var parameter 4 * SUB $end
$var parameter 4 + XOR $end
$var reg 32 , in_data1 [31:0] $end
$var reg 32 - in_data2 [31:0] $end
$var reg 4 . in_select [3:0] $end
$scope module DUT $end
$var wire 32 / in_data1 [31:0] $end
$var wire 32 0 in_data2 [31:0] $end
$var wire 4 1 in_select [3:0] $end
$var parameter 4 2 ADD $end
$var parameter 4 3 AND $end
$var parameter 4 4 OR $end
$var parameter 4 5 SET_LESS $end
$var parameter 4 6 SET_LESS_UNSIGNED $end
$var parameter 4 7 SHIFT_LEFT $end
$var parameter 4 8 SHIFT_RIGHT_ARITHMETIC $end
$var parameter 4 9 SHIFT_RIGHT_LOGICAL $end
$var parameter 4 : SUB $end
$var parameter 4 ; XOR $end
$var reg 32 < out_data [31:0] $end
$upscope $end
$upscope $end
$enddefinitions $end
$comment Show the parameter values. $end
$dumpall
b1000 ;
b0 :
b1010 9
b1011 8
b10 7
b110 6
b100 5
b1100 4
b1110 3
b0 2
b1000 +
b1 *
b1010 )
b1011 (
b10 '
b110 &
b100 %
b1100 $
b1110 #
b0 "
$end
#0
$dumpvars
b0 <
b0 1
b0 0
b0 /
b0 .
b0 -
b0 ,
b0 !
$end
#10
b11 !
b11 <
b10 -
b10 0
b1 ,
b1 /
#20
b0 !
b0 <
b1 .
b1 1
#30
b110 !
b110 <
b1000 .
b1000 1
b100 -
b100 0
b10 ,
b10 /
#40
b111 !
b111 <
b1100 .
b1100 1
b11 ,
b11 /
#50
b10 !
b10 <
b1110 .
b1110 1
b10 -
b10 0
#60
b100000 !
b100000 <
b10 .
b10 1
b101 -
b101 0
b1 ,
b1 /
#70
b1000 !
b1000 <
b1010 .
b1010 1
b1 -
b1 0
b10001 ,
b10001 /
#80
b11111111111111111111111111111111 !
b11111111111111111111111111111111 <
b1011 .
b1011 1
b10 -
b10 0
b11111111111111111111111111111111 ,
b11111111111111111111111111111111 /
#90
b1 !
b1 <
b100 .
b100 1
b101 -
b101 0
b11111111111111111111111111110110 ,
b11111111111111111111111111110110 /
#100
b0 !
b0 <
b1010 ,
b1010 /
#110
b110 .
b110 1
b11111111111111111111111111110110 ,
b11111111111111111111111111110110 /
#120
b1010 ,
b1010 /
#130
b1000 .
b1000 1
b1001 -
b1001 0
b1001 ,
b1001 /
